cipher_kit/__init__.py
cipher_kit/src/__init__.py
cipher_kit/src/cipher.py
cipher_kit/tests/__init__.py
cipher_kit/tests/test_cipher.py
cipher_kit-0.0.4.dist-info/LICENSE.txt
cipher_kit-0.0.4.dist-info/METADATA
cipher_kit-0.0.4.dist-info/WHEEL
cipher_kit-0.0.4.dist-info/top_level.txt
cipher_kit-0.0.4.dist-info/RECORD
