Metadata-Version: 2.1
Name: cipher-kit
Version: 0.0.4
Summary: Module which helps in encryption and decryption
Home-page: https://github.com/PankajVishw50/cipher_kit
Author: Pankaj
Author-email: pankaj.vishw.dev@gmail.com
Classifier: Programming Language :: Python
Classifier: Programming Language :: Python :: 3 
Classifier: License :: OSI Approved :: MIT License
License-File: LICENSE.txt
